tsboost/__init__.py
tsboost/ensembles.py
tsboost/regressors.py
tsboost-0.1.0.dist-info/DESCRIPTION.rst
tsboost-0.1.0.dist-info/METADATA
tsboost-0.1.0.dist-info/RECORD
tsboost-0.1.0.dist-info/WHEEL
tsboost-0.1.0.dist-info/metadata.json
tsboost-0.1.0.dist-info/top_level.txt
