Metadata-Version: 2.0
Name: tsboost
Version: 0.1.0
Summary: Time series Framework
Home-page: https://github.com/franck-durand/tsboost
Author: Franck Durand
Author-email: franck.durand@gadz.org
License: MIT license
Keywords: tsboost
Platform: UNKNOWN
Classifier: Development Status :: 2 - Pre-Alpha
Classifier: Intended Audience :: Developers
Classifier: License :: OSI Approved :: MIT License
Classifier: Natural Language :: English
Classifier: Programming Language :: Python :: 2
Classifier: Programming Language :: Python :: 2.7
Classifier: Programming Language :: Python :: 3
Classifier: Programming Language :: Python :: 3.5
Classifier: Programming Language :: Python :: 3.6
Classifier: Programming Language :: Python :: 3.7
Requires-Dist: lightgbm (>=2.2.1)
Requires-Dist: numpy
Requires-Dist: pandas (>=0.22.0)
Requires-Dist: xgboost (>=0.80)
